kuojingyueyi_api/__init__.py
kuojingyueyi_api/api.py
kuojingyueyi_api/exception.py
kuojingyueyi_api/fields.py
kuojingyueyi_api/utils.py
kuojingyueyi_api/versions.py
kuojingyueyi_api-0.5.0.dist-info/METADATA
kuojingyueyi_api-0.5.0.dist-info/WHEEL
kuojingyueyi_api-0.5.0.dist-info/top_level.txt
kuojingyueyi_api-0.5.0.dist-info/RECORD
