Metadata-Version: 2.1
Name: kuojingyueyi-api
Version: 0.5.0
Summary: 阔景Api接口
Home-page: https://github.com/ldsxp/kuojingyueyi-api
Author: lds
Author-email: 85176878@qq.com
License: GNU GPL 3
Download-URL: https://pypi.org/project/kuojingyueyi-api
Platform: any
Classifier: Development Status :: 5 - Production/Stable
Classifier: Intended Audience :: Developers
Classifier: License :: OSI Approved :: GNU General Public License (GPL)
Classifier: Operating System :: OS Independent
Classifier: Programming Language :: Python
Classifier: Programming Language :: Python :: 3.6
Requires-Dist: requests
Requires-Dist: loguru
